{"success":true,"data":{"output":{"results":[{"className":"car","score":"0.998","bbox":{"xmin":142,"ymin":326,"xmax":253,"ymax":422}},{"className":"car","score":"0.995","bbox":{"xmin":1071,"ymin":312,"xmax":1201,"ymax":408}},{"className":"car","score":"0.993","bbox":{"xmin":9,"ymin":406,"xmax":164,"ymax":582}},{"className":"car","score":"0.984","bbox":{"xmin":212,"ymin":259,"xmax":316,"ymax":342}},{"className":"car","score":"0.982","bbox":{"xmin":781,"ymin":298,"xmax":871,"ymax":402}},{"className":"car","score":"0.976","bbox":{"xmin":290,"ymin":482,"xmax":512,"ymax":765}},{"className":"car","score":"0.976","bbox":{"xmin":833,"ymin":353,"xmax":947,"ymax":473}},{"className":"car","score":"0.975","bbox":{"xmin":662,"ymin":281,"xmax":757,"ymax":396}},{"className":"car","score":"0.974","bbox":{"xmin":-1,"ymin":476,"xmax":105,"ymax":661}},{"className":"car","score":"0.971","bbox":{"xmin":760,"ymin":527,"xmax":938,"ymax":757}},{"className":"car","score":"0.962","bbox":{"xmin":717,"ymin":204,"xmax":854,"ymax":259}},{"className":"car","score":"0.947","bbox":{"xmin":427,"ymin":368,"xmax":535,"ymax":465}},{"className":"car","score":"0.944","bbox":{"xmin":269,"ymin":298,"xmax":373,"ymax":434}},{"className":"car","score":"0.939","bbox":{"xmin":566,"ymin":560,"xmax":805,"ymax":792}},{"className":"car","score":"0.802","bbox":{"xmin":141,"ymin":452,"xmax":302,"ymax":591}},{"className":"person","score":"0.990","bbox":{"xmin":1105,"ymin":428,"xmax":1149,"ymax":528}},{"className":"person","score":"0.979","bbox":{"xmin":1041,"ymin":596,"xmax":1122,"ymax":733}},{"className":"person","score":"0.935","bbox":{"xmin":1128,"ymin":557,"xmax":1195,"ymax":648}}]}}}